{
    "Common Rice Diseases": "ជំងឺស្រូវទូទៅ",
    "Home": "ទំព័រដើម",
    "Saved": "រក្សាទុក",
    "Profile": "ប្រវត្តិរូប",
    "No saved diagnoses yet!": "មិនមានការធ្វើវិនិច្ឆ័យដែលបានរក្សាទុកនៅឡើយទេ!",
    "Saved Diagnoses": "ការធ្វើវិនិច្ឆ័យដែលបានរក្សាទុក",
    "No diagnoses available": "មិនមានការធ្វើវិនិច្ឆ័យណាមួយទេ",
    "Error loading diagnoses": "កំហុសក្នុងការទាញយកការធ្វើវិនិច្ឆ័យ",
    "Recent Diagnoses": "ការធ្វើវិនិច្ឆ័យថ្មីៗ",
    "Your Reports": "របាយការណ៍របស់អ្នក",
    "Part of Disease": "ផ្នែកនៃជំងឺ",
    "No reports yet": "មិនមានរបាយការណ៍នៅឡើយទេ",
    "Your submitted reports will appear here": "របាយការណ៍ដែលអ្នកបានដាក់ស្នើនឹងបង្ហាញនៅទីនេះ",
    "Delete Report": "លុបរបាយការណ៍",
    "Are you sure you want to delete this report": "តើអ្នកប្រាកដជាចង់លុបរបាយការណ៍នេះទេ?",
    "Cancel": "បោះបង់",
    "Delete": "លុប",
    "Report submitted successfully!": "របាយការណ៍បានដាក់ស្នើដោយជោគជ័យ!",
    "Report updated successfully!": "របាយការណ៍បានធ្វើបច្ចុប្បន្នភាពដោយជោគជ័យ!",
    "Please fill in all fields and select an image.": "សូមបំពេញវាលទាំងអស់ និងជ្រើសរូបភាព។",
    "Report Disease": "រាយការណ៍ជំងឺ",
    "Report Details": "ព័ត៌មានលម្អិតរបាយការណ៍",
    "Edit Report": "កែសម្រួលរបាយការណ៍",
    "Description": "ការពិពណ៌នា",
    "Affected Part: ": "ផ្នែកដែលទាក់ទង: ",
    "Symptoms: ": "រោគសញ្ញា: ",
    "Management: ": "ការគ្រប់គ្រង: ",
    "Login": "ចូល",
    "Not a member yet?": "មិនមែនជាសមាជិកនៅឡើយទេ?",
    "Create an Account": "បង្កើតគណនី",
    "Position object within frame": "ដាក់វត្ថុក្នុងស៊ុម",
    "Scan Rice": "ស្កេនស្រូវ",
    "Processing...": "កំពុងដំណើរការ...",
    "Upload from Gallery": "បញ្ចូលពីបណ្ណាល័យរូបភាព",
    "Diagnosis saved": "ការធ្វើវិនិច្ឆ័យបានរក្សាទុក",
    "unknown": "មិនស្គាល់",
    "Unknown disease": "ជំងឺមិនស្គាល់",
    "No info": "គ្មានព័ត៌មាន",
    "Analysis Result": "លទ្ធផលវិភាគ",
    "Results": "លទ្ធផល",
    "Scan Again": "ស្កេនម្តងទៀត",
    "Classification": "ការបែងចែក",
    "Details": "ព័ត៌មានលម្អិត",
    "Confidence": "ការប្រាកដភាព",
    "Symptoms": "រោគសញ្ញា",
    "Management": "ការគ្រប់គ្រង",
    "Common Disease": "ជំងឺទូទៅ",
    "Manage": "គ្រប់គ្រង"

  }